odoo/addons/product_packaging_multi_barcode/README.rst
odoo/addons/product_packaging_multi_barcode/__init__.py
odoo/addons/product_packaging_multi_barcode/__manifest__.py
odoo/addons/product_packaging_multi_barcode/hooks.py
odoo/addons/product_packaging_multi_barcode/i18n/es.po
odoo/addons/product_packaging_multi_barcode/i18n/fr.po
odoo/addons/product_packaging_multi_barcode/i18n/it.po
odoo/addons/product_packaging_multi_barcode/i18n/product_packaging_multi_barcode.pot
odoo/addons/product_packaging_multi_barcode/models/__init__.py
odoo/addons/product_packaging_multi_barcode/models/product_barcode.py
odoo/addons/product_packaging_multi_barcode/models/product_packaging.py
odoo/addons/product_packaging_multi_barcode/readme/CONTRIBUTORS.rst
odoo/addons/product_packaging_multi_barcode/readme/CREDITS.rst
odoo/addons/product_packaging_multi_barcode/readme/DESCRIPTION.rst
odoo/addons/product_packaging_multi_barcode/readme/USAGE.rst
odoo/addons/product_packaging_multi_barcode/static/description/icon.png
odoo/addons/product_packaging_multi_barcode/static/description/index.html
odoo/addons/product_packaging_multi_barcode/tests/__init__.py
odoo/addons/product_packaging_multi_barcode/tests/test_product_packaging_multi_barcode.py
odoo/addons/product_packaging_multi_barcode/views/barcode_view.xml
odoo/addons/product_packaging_multi_barcode/views/product_packaging_view.xml
odoo_addon_product_packaging_multi_barcode-16.0.1.3.0.1.dist-info/METADATA
odoo_addon_product_packaging_multi_barcode-16.0.1.3.0.1.dist-info/WHEEL
odoo_addon_product_packaging_multi_barcode-16.0.1.3.0.1.dist-info/top_level.txt
odoo_addon_product_packaging_multi_barcode-16.0.1.3.0.1.dist-info/RECORD
