Metadata-Version: 2.1
Name: odoo-addon-product_packaging_multi_barcode
Version: 16.0.1.3.0.1
Summary: Multiple barcodes on product packagings
Home-page: https://github.com/OCA/stock-logistics-barcode
Author: Camptocamp, Odoo Community Association (OCA)
Author-email: support@odoo-community.org
License: AGPL-3
Classifier: Programming Language :: Python
Classifier: Framework :: Odoo
Classifier: Framework :: Odoo :: 16.0
Classifier: License :: OSI Approved :: GNU Affero General Public License v3
Requires-Python: >=3.10
Requires-Dist: odoo-addon-product-multi-barcode<16.1dev,>=16.0dev
Requires-Dist: odoo-addon-product-multi-barcode-stock-menu<16.1dev,>=16.0dev
Requires-Dist: odoo<16.1dev,>=16.0a
